{
  "path": "/app/.data/train/195820_000045.png",
  "width": 160,
  "height": 60,
  "image_format": "png",
  "bbox": [
    {
      "label": "1",
      "xmin": 23,
      "ymin": 0,
      "xmax": 47,
      "ymax": 59
    },
    {
      "label": "9",
      "xmin": 36,
      "ymin": 0,
      "xmax": 62,
      "ymax": 59
    },
    {
      "label": "5",
      "xmin": 53,
      "ymin": 0,
      "xmax": 74,
      "ymax": 59
    },
    {
      "label": "8",
      "xmin": 67,
      "ymin": 0,
      "xmax": 90,
      "ymax": 59
    },
    {
      "label": "2",
      "xmin": 83,
      "ymin": 0,
      "xmax": 113,
      "ymax": 59
    },
    {
      "label": "0",
      "xmin": 103,
      "ymin": 0,
      "xmax": 136,
      "ymax": 59
    }
  ]
}