{
  "path": "/app/.data/train/494567_006042.png",
  "width": 160,
  "height": 60,
  "image_format": "png",
  "bbox": [
    {
      "label": "4",
      "xmin": 18,
      "ymin": 0,
      "xmax": 54,
      "ymax": 59
    },
    {
      "label": "9",
      "xmin": 38,
      "ymin": 0,
      "xmax": 66,
      "ymax": 59
    },
    {
      "label": "4",
      "xmin": 57,
      "ymin": 0,
      "xmax": 85,
      "ymax": 59
    },
    {
      "label": "5",
      "xmin": 71,
      "ymin": 0,
      "xmax": 103,
      "ymax": 59
    },
    {
      "label": "6",
      "xmin": 88,
      "ymin": 0,
      "xmax": 126,
      "ymax": 59
    },
    {
      "label": "7",
      "xmin": 111,
      "ymin": 0,
      "xmax": 141,
      "ymax": 59
    }
  ]
}